rflask/__init__.py
rflask/commands.py
rflask/exceptions.py
rflask/files_content.py
rflask/rflask.py
rflask-1.1.6.dist-info/LICENSE
rflask-1.1.6.dist-info/METADATA
rflask-1.1.6.dist-info/WHEEL
rflask-1.1.6.dist-info/entry_points.txt
rflask-1.1.6.dist-info/top_level.txt
rflask-1.1.6.dist-info/RECORD
